LICENSE
MANIFEST.in
README.md
requirements.txt
setup.py
datrool_lib.egg-info/PKG-INFO
datrool_lib.egg-info/SOURCES.txt
datrool_lib.egg-info/dependency_links.txt
datrool_lib.egg-info/top_level.txt
src/__init__.py
src/logger.py
src/scheduler.py
src/validators.py