Metadata-Version: 2.1
Name: datrool-lib
Version: 1.0.4
Summary: Common library for the datrool project
Home-page: https://gitlab.com/datrool/core/lib
Author: Patrik Katrenak
Author-email: patrik@katryapps.com
Platform: any
Classifier: Programming Language :: Python :: 3
Classifier: Operating System :: OS Independent
Classifier: Natural Language :: English
Requires-Python: >=3.10
License-File: LICENSE
